pytimbr/__init__.py
pytimbr/timbr_connector.py
pytimbr/timbr_jdbapi.py
pytimbr/jars/hive-jdbc-4.0.1-standalone.jar
pytimbr-2.0.0.dist-info/licenses/LICENSE
pytimbr-2.0.0.dist-info/licenses/NOTICE
pytimbr-2.0.0.dist-info/METADATA
pytimbr-2.0.0.dist-info/WHEEL
pytimbr-2.0.0.dist-info/top_level.txt
pytimbr-2.0.0.dist-info/RECORD
