Metadata-Version: 2.4
Name: pytimbr
Version: 2.0.0
Summary: Timbr Python connector
Author-email: timbr <contact@timbr.ai>
License-Expression: MIT
Project-URL: Homepage, https://github.com/WPSemantix/timbr_python_connector
Project-URL: Download, https://github.com/WPSemantix/timbr_python_connector/releases
Project-URL: Bug Tracker, https://github.com/WPSemantix/timbr_python_connector/issues
Project-URL: Repository, https://github.com/WPSemantix/timbr_python_connector
Project-URL: Documentation, https://github.com/WPSemantix/timbr_python_connector#readme
Keywords: timbr,timbr-python,timbr-connector,python-connector,PyTimbr,pytimbr,py-timbr,Py-Timbr
Classifier: Development Status :: 5 - Production/Stable
Classifier: Intended Audience :: Developers
Classifier: Topic :: Software Development :: Build Tools
Classifier: Programming Language :: Python :: 3
Classifier: Programming Language :: Python :: 3.9
Classifier: Programming Language :: Python :: 3.10
Classifier: Programming Language :: Python :: 3.11
Classifier: Programming Language :: Python :: 3.12
Requires-Python: >=3.9
License-File: LICENSE
License-File: NOTICE
Requires-Dist: JPype1==1.5.1
Requires-Dist: pandas==1.3.5
Requires-Dist: numpy==1.26.4
Dynamic: license-file
